debugmate/__init__.py
debugmate/utils.py
debugmate/context/__init__.py
debugmate/context/environment_context.py
debugmate/context/request_context.py
debugmate/context/stack_trace_context.py
debugmate/django/__init__.py
debugmate/django/middleware.py
debugmate/handlers/__init__.py
debugmate/handlers/debugmate_handler.py
debugmate-0.0.1.dist-info/LICENSE
debugmate-0.0.1.dist-info/METADATA
debugmate-0.0.1.dist-info/WHEEL
debugmate-0.0.1.dist-info/top_level.txt
debugmate-0.0.1.dist-info/RECORD
