Metadata-Version: 2.1
Name: debugmate
Version: 0.0.1
Summary: Debugmate client package
Author-email: Devsquad <ti@devsquad.com>
Project-URL: Homepage, https://github.com/DebugMate/python
Project-URL: Issues, https://github.com/DebugMate/python/issues
Classifier: Programming Language :: Python :: 3
Classifier: License :: OSI Approved :: MIT License
Classifier: Operating System :: OS Independent
Requires-Python: >=3.8
License-File: LICENSE
Requires-Dist: django
Requires-Dist: requests
